stocklake/__init__.py
stocklake/environment_variables.py
stocklake/exceptions.py
stocklake/cli/__init__.py
stocklake/core/__init__.py
stocklake/core/base_data_loader.py
stocklake/core/base_pipeline.py
stocklake/core/base_preprocessor.py
stocklake/core/base_sqlalchemy_store.py
stocklake/core/base_store.py
stocklake/core/constants.py
stocklake/core/stdout.py
stocklake/entities/__init__.py
stocklake/entities/file_info.py
stocklake/nasdaqapi/README.md
stocklake/nasdaqapi/__init__.py
stocklake/nasdaqapi/cli.py
stocklake/nasdaqapi/constants.py
stocklake/nasdaqapi/data_loader.py
stocklake/nasdaqapi/entities.py
stocklake/nasdaqapi/pipeline.py
stocklake/nasdaqapi/preprocessor.py
stocklake/nasdaqapi/stores.py
stocklake/nasdaqapi/utils.py
stocklake/polygonapi/__init__.py
stocklake/polygonapi/cli.py
stocklake/polygonapi/utils.py
stocklake/polygonapi/validation.py
stocklake/polygonapi/aggregates_bars/__init__.py
stocklake/polygonapi/aggregates_bars/cli.py
stocklake/polygonapi/aggregates_bars/data_loader.py
stocklake/polygonapi/aggregates_bars/entities.py
stocklake/polygonapi/aggregates_bars/pipeline.py
stocklake/polygonapi/aggregates_bars/preprocessor.py
stocklake/polygonapi/aggregates_bars/stores.py
stocklake/polygonapi/stock_financials_vx/__init__.py
stocklake/polygonapi/stock_financials_vx/cli.py
stocklake/polygonapi/stock_financials_vx/data_loader.py
stocklake/polygonapi/stock_financials_vx/entities.py
stocklake/polygonapi/stock_financials_vx/pipeline.py
stocklake/polygonapi/stock_financials_vx/preprocessor.py
stocklake/polygonapi/stock_financials_vx/stores.py
stocklake/stores/__init__.py
stocklake/stores/alembic.ini
stocklake/stores/constants.py
stocklake/stores/artifact/__init__.py
stocklake/stores/artifact/base.py
stocklake/stores/artifact/local_artifact_repo.py
stocklake/stores/db/__init__.py
stocklake/stores/db/cli.py
stocklake/stores/db/database.py
stocklake/stores/db/models.py
stocklake/stores/db/utils.py
stocklake/stores/db_migrations/README
stocklake-0.0.16.dist-info/METADATA
stocklake-0.0.16.dist-info/WHEEL
stocklake-0.0.16.dist-info/entry_points.txt
stocklake-0.0.16.dist-info/licenses/LICENSE.txt
stocklake-0.0.16.dist-info/RECORD
