Metadata-Version: 2.3
Name: stocklake
Version: 0.0.16
License-Expression: MIT
License-File: LICENSE.txt
Requires-Dist: alembic
Requires-Dist: beautifulsoup4
Requires-Dist: click
Requires-Dist: pandas
Requires-Dist: polygon-api-client
Requires-Dist: psycopg2-binary
Requires-Dist: pydantic
Requires-Dist: python-dotenv
Requires-Dist: requests
Requires-Dist: sqlalchemy-utils
Provides-Extra: dev
Requires-Dist: black; extra == 'dev'
Requires-Dist: mypy; extra == 'dev'
Requires-Dist: pre-commit; extra == 'dev'
Requires-Dist: pytest; extra == 'dev'
Requires-Dist: ruff-lsp; extra == 'dev'
